{
    "今開": "1095.00",
    "最高": "1100.00",
    "成交量": "22,275",
    "昨收": "1090.00",
    "最低": "1090.00",
    "成交額": "244.12億",
    "均價": "1095.94",
    "本益比": "21.78",
    "市值": "28.53兆",
    "振幅": "0.92%",
    "週轉率": "0.09%",
    "發行股": "259.33億",
    "漲停": "1195.00",
    "52W高": "1160.00",
    "內盤量": "9,017",
    "跌停": "981.00",
    "52W低": "780.00",
    "外盤量": "13,258",
    "近四季EPS": "50.50",
    "當季EPS": "13.95",
    "毛利率": "58.79%",
    "每股淨值": "176.00",
    "本淨比": "6.25",
    "營益率": "48.51%",
    "年股利": "9.00",
    "殖利率": "1.56%",
    "淨利率": "42.98%"
}